setup.py
epitome_tools/__init__.py
epitome_tools/atlas.py
epitome_tools/celltyping.py
epitome_tools/doublets.py
epitome_tools/epitome_files.py
epitome_tools/workflow.py
epitome_tools.egg-info/PKG-INFO
epitome_tools.egg-info/SOURCES.txt
epitome_tools.egg-info/dependency_links.txt
epitome_tools.egg-info/requires.txt
epitome_tools.egg-info/top_level.txt
epitome_tools/models/atac_final_threshold.pkl
epitome_tools/models/atac_label_encoder_binary.pkl
epitome_tools/models/atac_model.json
epitome_tools/models/atac_model_binary.json
epitome_tools/models/final_threshold.pkl
epitome_tools/models/label_encoder_atac.pkl
epitome_tools/models/label_encoder_rna.pkl
epitome_tools/models/rna_label_encoder_binary.pkl
epitome_tools/models/rna_model.json
epitome_tools/models/rna_model_binary.json