Metadata-Version: 2.1
Name: epitome_tools
Version: 0.0.21
Summary: Auxiliary tools for the Consensus Pituitary Atlas
Author: Bence Kover
Author-email: <kover.bence@gmail.com>
Keywords: xgboost,annotation,celltype,doublet
Classifier: Development Status :: 1 - Planning
Classifier: Intended Audience :: Science/Research
Classifier: Programming Language :: Python :: 3
Classifier: Operating System :: MacOS :: MacOS X
Requires-Dist: xgboost
Requires-Dist: scipy
Requires-Dist: numpy
